Metadata-Version: 1.0
Name: dtrs-gaussian-binomial
Version: 1.2
Summary: Gaussian and Binomial distributions
Home-page: UNKNOWN
Author: ons cherif
Author-email: oscheriff@gmail.com
License: UNKNOWN
Platform: UNKNOWN
